{"DMK":"BKK","BKK":"BKK","ESB":"ANK","HBE":"ALY","ALY":"ALY","AUH":"AUH","AZI":"AUH","ACY":"AIY","AIY":"AIY","GBO":"WAS","BWI":"WAS","BZS":"WAS","MTN":"WAS","DCA":"WAS","IAD":"WAS","MKC":"MKC","MCI":"MKC","VIE":"VIE","YND":"YOW","YOW":"YOW","YRO":"YOW","TFN":"TCI","TFS":"TCI","MMX":"MMA","BHD":"BFS","BFS":"BFS","GIG":"RIO","SDU":"RIO","STX":"STX","KBP":"IEV","IEV":"IEV","XIY":"SIA","SIA":"SIA","RSW":"FMY","FMY":"FMY","BKA":"MOW","DME":"MOW","SVO":"MOW","VKO":"MOW","IKA":"THR","THR":"THR","CRL":"BRU","BRU":"BRU","ILE":"ILE","ADB":"IZM","IGL":"IZM","CVG":"CVG","LUK":"CVG","CIU":"SSM","ORL":"ORL","MCO":"ORL","SFB":"ORL","DWS":"ORL","BFI":"SEA","SEA":"SEA","PAE":"SEA","CGH":"SAO","GRU":"SAO","VCP":"SAO","PIE":"TPA","TPF":"TPA","TPA":"TPA","KYO":"TPA","UVF":"SLU","SLU":"SLU","LIN":"MIL","MXP":"MIL","BGY":"MIL","PMF":"MIL","LWK":"SDZ","SCS":"SDZ","LSI":"SDZ","AXS":"LTS","SBS":"SBS","HDN":"SBS","MUV":"QPH","PNE":"QPH","PHL":"QPH","TTN":"QPH","GYD":"BAK","ZXT":"BAK","DAL":"QDF","DFW":"QDF","AFW":"QDF","FTW":"QDF","LIL":"LIL","YEG":"YEA","YXD":"YEA","BBU":"BUH","OTP":"BUH","LYN":"LYS","GNB":"LYS","LYS":"LYS","PFN":"PFN","ECP":"PFN","LNZ":"LNZ","SXB":"SXB","CIA":"ROM","FCO":"ROM","DET":"DTT","DTW":"DTT","ARB":"DTT","YIP":"DTT","YMX":"YMQ","YUL":"YMQ","YHU":"YMQ","SZF":"SSX","ITM":"OSA","KIX":"OSA","UKB":"OSA","KNO":"MES","MES":"MES","YKZ":"YTO","YHM":"YTO","YKF":"YTO","YYZ":"YTO","YTZ":"YTO","MDW":"CHI","ORD":"CHI","DPA":"CHI","RFD":"CHI","PWK":"CHI","GYY":"CHI","DUS":"DUS","MGL":"DUS","NRN":"DUS","EMA":"NQT","NQT":"NQT","AVV":"MEL","MEB":"MEL","MBW":"MEL","MEL":"MEL","IST":"IST","SAW":"IST","MLH":"EAP","BSL":"EAP","PLU":"BHZ","CNF":"BHZ","HLP":"JKT","CGK":"JKT","STR":"STR","BQH":"LON","LGW":"LON","LHR":"LON","LCY":"LON","LTN":"LON","SEN":"LON","STN":"LON","SRZ":"SRZ","VVI":"SRZ","KEF":"REK","RKV":"REK","FLR":"FLR","ARN":"STO","BMA":"STO","NYO":"STO","VST":"STO","MDT":"HAR","EFD":"QHO","IAH":"QHO","SGR":"QHO","HOU":"QHO","KUL":"KUL","SZB":"KUL","CGN":"CGN","SHA":"SHA","PVG":"SHA","BDL":"HFD","HFD":"HFD","FYV":"FYV","XNA":"FYV","JFK":"NYC","LGA":"NYC","EWR":"NYC","CTS":"SPK","OKD":"SPK","WCA":"WCA","MHC":"WCA","DWC":"DXB","DXB":"DXB","BVA":"PAR","CDG":"PAR","LBG":"PAR","ORY":"PAR","POX":"PAR","XCR":"PAR","CLK":"CSM","GMP":"SEL","ICN":"SEL","ROB":"MLW","MLW":"MLW","TPE":"TPE","TSA":"TPE","HND":"TYO","NRT":"TYO","CMN":"CAS","RYG":"OSL","OSL":"OSL","TRF":"OSL","CXR":"NHA","BER":"BER","SXF":"BER","TXL":"BER","ULV":"ULY","ULY":"ULY","EZE":"BUE","BXN":"BXN","BJV":"BXN","PEK":"BJS"}